MANIFEST.in
README.md
setup.py
./README.md
Alchem_Event.egg-info/PKG-INFO
Alchem_Event.egg-info/SOURCES.txt
Alchem_Event.egg-info/dependency_links.txt
Alchem_Event.egg-info/requires.txt
Alchem_Event.egg-info/top_level.txt
alchemevent/__init__.py
alchemevent/event/base.c
alchemevent/event/base.pyx
alchemevent/kdutils/__init__.py
alchemevent/kdutils/base.c
alchemevent/kdutils/base.pyx
alchemevent/kdutils/create_id.c
alchemevent/kdutils/create_id.pyx
alchemevent/kdutils/lazy.c
alchemevent/kdutils/lazy.pyx
requirements/py3.txt