Metadata-Version: 2.1
Name: Alchem-Event
Version: 0.0.1
Summary: FinAlchem 0.0.1
Home-page: https://github.com/flaght
Author: flaght
Author-email: flaght@gmail.com
